LICENSE
README.md
setup.py
alps/__init__.py
alps/alps.py
alps/descriptors.py
alps/docs.py
alps/schemaorg.py
alps_py.egg-info/PKG-INFO
alps_py.egg-info/SOURCES.txt
alps_py.egg-info/dependency_links.txt
alps_py.egg-info/requires.txt
alps_py.egg-info/top_level.txt