Metadata-Version: 2.1
Name: alps-py
Version: 0.2.0
Summary: An ALPS library for python
Home-page: https://github.com/michalporeba/alps-py/
Author: Michal Poreba
License: MIT
Platform: UNKNOWN
Classifier: Development Status :: 3 - Alpha
Classifier: License :: OSI Approved :: MIT License
Classifier: Programming Language :: Python :: 3
Classifier: Intended Audience :: Developers
Classifier: Topic :: Software Development
License-File: LICENSE
